rgwml/__init__.py
rgwml/m.py
rgwml/p.py
rgwml-0.0.345.dist-info/LICENSE
rgwml-0.0.345.dist-info/METADATA
rgwml-0.0.345.dist-info/WHEEL
rgwml-0.0.345.dist-info/entry_points.txt
rgwml-0.0.345.dist-info/top_level.txt
rgwml-0.0.345.dist-info/RECORD
