Metadata-Version: 2.2
Name: rgwml
Version: 0.0.345
Summary: Manipulate data with code that is less a golden retriever, and more a Samurai's sword
Home-page: https://github.com/ryangerardwilson/rgwml_py
Author: Ryan Gerard Wilson
Author-email: Ryan Gerard Wilson <ryangerardwilson@gmail.com>
Project-URL: Homepage, https://github.com/ryangerardwilson/rgwml_py
Project-URL: Issues, https://github.com/ryangerardwilson/rgwml_py
Classifier: Programming Language :: Python :: 3
Classifier: License :: OSI Approved :: MIT License
Classifier: Operating System :: OS Independent
Requires-Python: >=3.8
License-File: LICENSE
Requires-Dist: pandas
Requires-Dist: numpy<2.0.0
Requires-Dist: pymssql
Requires-Dist: mysql-connector-python
Requires-Dist: clickhouse-connect
Requires-Dist: google-cloud-bigquery
Requires-Dist: google-auth
Requires-Dist: google-cloud-storage
Requires-Dist: google-auth-oauthlib
Requires-Dist: google-auth-httplib2
Requires-Dist: google-api-python-client
Requires-Dist: pandas-gbq
Requires-Dist: xgboost
Requires-Dist: matplotlib
Requires-Dist: pillow
Requires-Dist: scipy
Requires-Dist: seaborn
Requires-Dist: scikit-learn
Requires-Dist: pyarrow
Requires-Dist: distributed
Requires-Dist: requests
Requires-Dist: pymysql
Requires-Dist: openai
Requires-Dist: filetype
Requires-Dist: tqdm
Requires-Dist: requests-html
Requires-Dist: openai-whisper
Requires-Dist: slack-sdk
Requires-Dist: lxml[html_clean]
